{"type": "root", "attrs": {"type": "include"}, "body": [{"type": "dt_group", "body": [{"type": "dt", "indent": 0, "text": ["Environment Variables"], "extent": [16, 39], "body": [{"type": "para", "indent": 4, "text": ["Additional work item environment variables can be specified here.  These will be added to the job\u2019s environment.  If the value of the variable is empty, it will be removed from the job\u2019s environment."], "extent": [61, 266]}, {"type": "dt_group", "body": [{"type": "dt", "indent": 4, "text": ["Name"], "extent": [266, 276], "body": [{"type": "para", "indent": 8, "text": ["Name of the work item environment variable."], "extent": [305, 366]}], "container": true, "attrs": {"id": "local_envname#"}}, {"type": "dt", "indent": 4, "text": ["Value"], "extent": [366, 377], "body": [{"type": "para", "indent": 8, "text": ["Value of the work item environment variable."], "extent": [407, 461]}], "container": true, "attrs": {"id": "local_envvalue#"}}], "container": true}], "container": true, "attrs": {"id": "pdg_env_vars"}}], "container": true}, {"type": "para", "indent": 0, "text": ["Specifies an environment file for environment variables to be added to the job\u2019s environment. An environment variable from the file will overwrite an existing environment variable if they share identical names."], "extent": [461, 672], "body": [], "container": true, "attrs": {"id": "pdg_env_file_txt"}}]}